LICENSE
MANIFEST.in
README.md
requirements.txt
setup.cfg
setup.py
dvdp/__init__.py
dvdp.utils.egg-info/PKG-INFO
dvdp.utils.egg-info/SOURCES.txt
dvdp.utils.egg-info/dependency_links.txt
dvdp.utils.egg-info/requires.txt
dvdp.utils.egg-info/top_level.txt
dvdp/utils/__init__.py
dvdp/utils/__main__.py
dvdp/utils/checkerboard.py
dvdp/utils/data.py
dvdp/utils/system.py
dvdp/utils/apt_package/__init__.py
dvdp/utils/apt_package/__main__.py
dvdp/utils/apt_package/apt_package.py
dvdp/utils/apt_package/test_apt_package.py
dvdp/utils/apt_package/test_data.py