Metadata-Version: 2.1
Name: dvdp.utils
Version: 0.0.5
Summary: Python utilities.
Home-page: https://github.com/davidvdp/utils
Author: David van der Pol
Author-email: david@davidvanderpol.com
License: MIT
Download-URL: https://github.com/davidvdp/utils/archive/v0.0.5.tar.gz
Keywords: Utils
Platform: UNKNOWN
Classifier: Intended Audience :: Developers
Classifier: License :: OSI Approved :: MIT License
Classifier: Programming Language :: Python :: 3
Classifier: Programming Language :: Python :: 3.7
